giphy_hive_test2_sdk/__init__.py
giphy_hive_test2_sdk/api_client.py
giphy_hive_test2_sdk/api_response.py
giphy_hive_test2_sdk/configuration.py
giphy_hive_test2_sdk/exceptions.py
giphy_hive_test2_sdk/py.typed
giphy_hive_test2_sdk/rest.py
giphy_hive_test2_sdk/api/__init__.py
giphy_hive_test2_sdk/api/gifs_api.py
giphy_hive_test2_sdk/api/stickers_api.py
giphy_hive_test2_sdk/models/__init__.py
giphy_hive_test2_sdk/models/get_gifs_by_id200_response.py
giphy_hive_test2_sdk/models/gif.py
giphy_hive_test2_sdk/models/gif_images.py
giphy_hive_test2_sdk/models/gif_images_downsized.py
giphy_hive_test2_sdk/models/gif_images_downsized_large.py
giphy_hive_test2_sdk/models/gif_images_downsized_medium.py
giphy_hive_test2_sdk/models/gif_images_downsized_small.py
giphy_hive_test2_sdk/models/gif_images_downsized_still.py
giphy_hive_test2_sdk/models/gif_images_fixed_height.py
giphy_hive_test2_sdk/models/gif_images_fixed_height_downsampled.py
giphy_hive_test2_sdk/models/gif_images_fixed_height_small.py
giphy_hive_test2_sdk/models/gif_images_fixed_height_small_still.py
giphy_hive_test2_sdk/models/gif_images_fixed_height_still.py
giphy_hive_test2_sdk/models/gif_images_fixed_width.py
giphy_hive_test2_sdk/models/gif_images_fixed_width_downsampled.py
giphy_hive_test2_sdk/models/gif_images_fixed_width_small.py
giphy_hive_test2_sdk/models/gif_images_fixed_width_small_still.py
giphy_hive_test2_sdk/models/gif_images_fixed_width_still.py
giphy_hive_test2_sdk/models/gif_images_looping.py
giphy_hive_test2_sdk/models/gif_images_original.py
giphy_hive_test2_sdk/models/gif_images_original_still.py
giphy_hive_test2_sdk/models/gif_images_preview.py
giphy_hive_test2_sdk/models/gif_images_preview_gif.py
giphy_hive_test2_sdk/models/image.py
giphy_hive_test2_sdk/models/meta.py
giphy_hive_test2_sdk/models/pagination.py
giphy_hive_test2_sdk/models/random_gif200_response.py
giphy_hive_test2_sdk/models/user.py
giphy_hive_test2_sdk-0.0.7.dist-info/METADATA
giphy_hive_test2_sdk-0.0.7.dist-info/WHEEL
giphy_hive_test2_sdk-0.0.7.dist-info/top_level.txt
giphy_hive_test2_sdk-0.0.7.dist-info/RECORD
